{"job":{"type":"presubmit","job":"pull-test-dev-rerere","buildid":"1414467386915950592","prowjobid":"f9387471-e2d7-11eb-8cbd-7613f303724b","refs":{"org":"ti-community-infra","repo":"test-dev","repo_link":"https://github.com/ti-community-infra/test-dev","base_ref":"master","base_sha":"1e2b783eb97189236601f06849d673f58719de0b","base_link":"https://github.com/ti-community-infra/test-dev/commit/1e2b783eb97189236601f06849d673f58719de0b","pulls":[{"number":406,"author":"Mini256","sha":"9cd72f7cf65f0eff1d8d599b7b34c11d4e506ed1","title":"feat: update README","link":"https://github.com/ti-community-infra/test-dev/pull/406","commit_link":"https://github.com/ti-community-infra/test-dev/pull/406/commits/9cd72f7cf65f0eff1d8d599b7b34c11d4e506ed1","author_link":"https://github.com/Mini256"}]},"decoration_config":{"utility_images":{"clonerefs":"gcr.io/k8s-prow/clonerefs:v20210701-3efe91b8cd","initupload":"gcr.io/k8s-prow/initupload:v20210701-3efe91b8cd","entrypoint":"gcr.io/k8s-prow/entrypoint:v20210701-3efe91b8cd","sidecar":"gcr.io/k8s-prow/sidecar:v20210701-3efe91b8cd"},"gcs_configuration":{"bucket":"gs://prow-dev-tidb-logs","path_strategy":"explicit"},"gcs_credentials_secret":"gcs-credentials"}},"options":{"retesting-branch":"try","retry":3,"require_contexts":{},"timeout":900000000000},"current_retry_times":1,"time":"2021-07-12T06:14:30.438937454Z"}